<?xml version = '1.0' encoding = 'UTF-8'?>
<Relation class="oracle.dbtools.crest.model.design.logical.Relation" name="Class_Settingv3" directorySegmentName="seg_0" id="A6E39E13-D0D8-5587-36A2-C8184A259A1F">
<createdBy>mgreiner</createdBy>
<createdTime>2017-08-30 17:59:28 UTC</createdTime>
<ownerDesignName>ClassDojo Part 2 Start File</ownerDesignName>
<engineerTo>
<item key="406D10FD-2772-B1D9-65D7-9047B1670112" value="true"/>
</engineerTo>
<targetPk>D46F4AD8-DEB8-F169-8F1E-9919CDD3CD84</targetPk>
<identifying>false</identifying>
<nameOnSource>favorited by</nameOnSource>
<nameOnTarget>favorites</nameOnTarget>
<optionalSource>false</optionalSource>
<optionalTarget>true</optionalTarget>
<sourceCardinality>*</sourceCardinality>
<sourceEntity>5C2264B2-6B6D-DFFB-145A-D04387A3BCC3</sourceEntity>
<targetCardinalityString>1</targetCardinalityString>
<targetEntity>21EB887B-F5D7-CC82-68C2-6E86566193E8</targetEntity>
<transferable>true</transferable>
<deleteRule>CASCADE</deleteRule>
</Relation>